errandkun/__init__.py
errandkun/errandkun.py
errandkun/external_resources/__init__.py
errandkun/external_resources/base.py
errandkun/external_resources/github.py
errandkun-0.0.6.dist-info/METADATA
errandkun-0.0.6.dist-info/WHEEL
errandkun-0.0.6.dist-info/entry_points.txt
errandkun-0.0.6.dist-info/top_level.txt
errandkun-0.0.6.dist-info/RECORD
